.gitattributes
.gitignore
.readthedocs.yml
.travis.yml
Apache-License-2.0.txt
LICENSE
MANIFEST.in
OFL-License.txt
README.rst
babel.cfg
funtooify.sh
package-lock.json
package.json
setup.cfg
setup.py
tox.ini
webpack.common.js
webpack.dev.js
webpack.prod.js
.github/CODE_OF_CONDUCT.md
.github/ISSUE_TEMPLATE.md
.tx/config
bin/preinstall.js
docs/Makefile
docs/changelog.rst
docs/conf.py
docs/configuring.rst
docs/contributing.rst
docs/index.rst
docs/installing.rst
docs/make.bat
docs/requirements.txt
docs/_static/debug.js
docs/_templates/layout.html
docs/demo/api.rst
docs/demo/demo.rst
docs/demo/lists_tables.rst
docs/demo/long.rst
docs/demo/structure.rst
docs/demo/static/logo-wordmark-light.svg
docs/demo/static/screen_desktop.png
docs/demo/static/screen_mobile.png
docs/demo/static/yi_jing_01_chien.jpg
docs/demo/test_py_module/__init__.py
docs/demo/test_py_module/test.py
sphinx_funtoo_theme/__init__.py
sphinx_funtoo_theme/breadcrumbs.html
sphinx_funtoo_theme/footer.html
sphinx_funtoo_theme/layout.html
sphinx_funtoo_theme/search.html
sphinx_funtoo_theme/searchbox.html
sphinx_funtoo_theme/theme.conf
sphinx_funtoo_theme/versions.html
sphinx_funtoo_theme.egg-info/PKG-INFO
sphinx_funtoo_theme.egg-info/SOURCES.txt
sphinx_funtoo_theme.egg-info/dependency_links.txt
sphinx_funtoo_theme.egg-info/entry_points.txt
sphinx_funtoo_theme.egg-info/not-zip-safe
sphinx_funtoo_theme.egg-info/requires.txt
sphinx_funtoo_theme.egg-info/top_level.txt
sphinx_funtoo_theme/locale/sphinx.pot
sphinx_funtoo_theme/locale/de/LC_MESSAGES/sphinx.mo
sphinx_funtoo_theme/locale/de/LC_MESSAGES/sphinx.po
sphinx_funtoo_theme/locale/en/LC_MESSAGES/sphinx.mo
sphinx_funtoo_theme/locale/en/LC_MESSAGES/sphinx.po
sphinx_funtoo_theme/locale/es/LC_MESSAGES/sphinx.mo
sphinx_funtoo_theme/locale/es/LC_MESSAGES/sphinx.po
sphinx_funtoo_theme/locale/et/LC_MESSAGES/sphinx.mo
sphinx_funtoo_theme/locale/et/LC_MESSAGES/sphinx.po
sphinx_funtoo_theme/locale/fr/LC_MESSAGES/sphinx.mo
sphinx_funtoo_theme/locale/fr/LC_MESSAGES/sphinx.po
sphinx_funtoo_theme/locale/nl/LC_MESSAGES/sphinx.mo
sphinx_funtoo_theme/locale/nl/LC_MESSAGES/sphinx.po
sphinx_funtoo_theme/locale/pt_BR/LC_MESSAGES/sphinx.mo
sphinx_funtoo_theme/locale/pt_BR/LC_MESSAGES/sphinx.po
sphinx_funtoo_theme/locale/ru/LC_MESSAGES/sphinx.mo
